scipyy/Adaline_Error_vs_Epoch _Graph.py
scipyy/Adaline_Implementation.py
scipyy/Compare_different_crossover_mutation_rates.py
scipyy/Hebbian_Learning_Binary_InputOutput.py
scipyy/Hebbian_Learning_Modified_Inputs.py
scipyy/Implement_GA_to_maximize.py
scipyy/McCulloch_Pitts_Neuron_for_OR_Gate.py
scipyy/McCulloch_Pitts_neuron_for_AND_gate.py
scipyy/Perceptron_for_AND_Gate.py
scipyy/SOM_Implementation _on_Data.py
scipyy/Visualizing_Neighbourhood_Effects.py
scipyy/XOR _Problem_with_Backpropagation.py
scipyy/__init__.py
scipyy/fuzzy_and_or _not_operation.py
scipyy/plot_triangular_and_trapezoidal _membership.py
scipyy/simple _fuzzy _inference _system_fis.py
scipyy-1.1.5.dist-info/licenses/LICENSE
scipyy-1.1.5.dist-info/METADATA
scipyy-1.1.5.dist-info/WHEEL
scipyy-1.1.5.dist-info/top_level.txt
scipyy-1.1.5.dist-info/RECORD
