Metadata-Version: 2.4
Name: scipyy
Version: 1.1.5
Summary: Hi How Are You Doing
Home-page: 
Author: Spoof
Author-email: xyz@gmail.com
License: MIT
Classifier: Programming Language :: Python :: 3
Classifier: Operating System :: OS Independent
Requires-Python: >=3.6
License-File: LICENSE
Dynamic: author
Dynamic: author-email
Dynamic: classifier
Dynamic: description-content-type
Dynamic: license
Dynamic: license-file
Dynamic: requires-python
Dynamic: summary
